crystalgen/__init__.py
crystalgen-2024.11.30.dist-info/LICENSE
crystalgen-2024.11.30.dist-info/METADATA
crystalgen-2024.11.30.dist-info/WHEEL
crystalgen-2024.11.30.dist-info/top_level.txt
crystalgen-2024.11.30.dist-info/RECORD
