Metadata-Version: 2.2
Name: crystalgen
Version: 2024.11.30
Summary: CrystalGen: Generative atomistic materials design toolkit
Home-page: https://github.com/atomgptlab/crystalgen
Author: Charles Campbell, Kamal Choudhary
Author-email: kchoudh2@jhu.edu
Classifier: Programming Language :: Python :: 3
Classifier: License :: OSI Approved :: MIT License
Classifier: Operating System :: OS Independent
Requires-Python: >=3.8
License-File: LICENSE
Requires-Dist: numpy>=1.22.0
Requires-Dist: scipy>=1.6.3
Requires-Dist: jarvis-tools>=2021.07.19
Requires-Dist: pydantic_settings
Requires-Dist: pandas
Dynamic: author
Dynamic: author-email
Dynamic: classifier
Dynamic: description
Dynamic: description-content-type
Dynamic: home-page
Dynamic: requires-dist
Dynamic: requires-python
Dynamic: summary
